argminer/__init__.py
argminer/config.py
argminer/data.py
argminer/evaluation.py
argminer/run_api.py
argminer/utils.py
argminer/api/__init__.py
argminer/api/utils.py
argminer/api/views.py
argminer/api/specs/__init__.py
argminer/api/specs/api.yaml
argminer/tests/__init__.py
argminer/tests/run_bigbird.py
argminer-0.1.0.dist-info/AUTHORS.md
argminer-0.1.0.dist-info/LICENSE
argminer-0.1.0.dist-info/METADATA
argminer-0.1.0.dist-info/WHEEL
argminer-0.1.0.dist-info/entry_points.txt
argminer-0.1.0.dist-info/top_level.txt
argminer-0.1.0.dist-info/RECORD
