Metadata-Version: 2.1
Name: argminer
Version: 0.1.0
Summary: A package for processing SOTA argument mining datasets
Home-page: https://github.com/namiyousef/argument-mining
Author: Yousef Nami
Author-email: namiyousef@hotmail.com
License: MIT
Platform: UNKNOWN
License-File: LICENSE
License-File: AUTHORS.md
Requires-Dist: torch
Requires-Dist: transformers
Requires-Dist: sentencepiece
Requires-Dist: pandas
Requires-Dist: plac
Requires-Dist: numpy
Requires-Dist: tqdm
Requires-Dist: sklearn
Requires-Dist: protobuf
Requires-Dist: colab-dev-tools
Requires-Dist: matplotlib
Requires-Dist: ml-dev-tools
Requires-Dist: connexion[swagger-ui]
